p_connector_dfg/Utilities.py
p_connector_dfg/__init__.py
p_connector_dfg/privacyPreserving.py
p_connector_dfg-0.0.14.dist-info/LICENSE
p_connector_dfg-0.0.14.dist-info/METADATA
p_connector_dfg-0.0.14.dist-info/WHEEL
p_connector_dfg-0.0.14.dist-info/pbr.json
p_connector_dfg-0.0.14.dist-info/top_level.txt
p_connector_dfg-0.0.14.dist-info/RECORD
